[
    {
        "numero_laudo": "0170087",
        "data_emissao": "28/10/2025",
        "data_validade": "12/11/2025",
        "cpf_cnpj_cliente": "41851003000116",
        "nome_cliente": "CVD ALIMENTOS LTDA",
        "quantidade_caixas": "255",
        "modelo_caixas": "6424"
    },
    {
        "numero_laudo": "0170088",
        "data_emissao": "28/10/2025",
        "data_validade": "12/11/2025",
        "cpf_cnpj_cliente": "41851003000116",
        "nome_cliente": "CVD ALIMENTOS LTDA",
        "quantidade_caixas": "255",
        "modelo_caixas": "6424"
    },
    {
        "numero_laudo": "0170089",
        "data_emissao": "28/10/2025",
        "data_validade": "12/11/2025",
        "cpf_cnpj_cliente": "19.886.150/0005-04",
        "nome_cliente": "UVALE FRUTAS TROPICAIS ",
        "quantidade_caixas": "800",
        "modelo_caixas": "6424"
    },
    {
        "numero_laudo": "0170090",
        "data_emissao": "29/10/2025",
        "data_validade": "13/11/2025",
        "cpf_cnpj_cliente": "41851003000116",
        "nome_cliente": "CVD ALIMENTOS LTDA",
        "quantidade_caixas": "325",
        "modelo_caixas": "6424"
    },
    {
        "numero_laudo": "0170091",
        "data_emissao": "29/10/2025",
        "data_validade": "13/11/2025",
        "cpf_cnpj_cliente": "41851003000116",
        "nome_cliente": "CVD ALIMENTOS LTDA",
        "quantidade_caixas": "325",
        "modelo_caixas": "6424"
    },
    {
        "numero_laudo": "0170092",
        "data_emissao": "30/10/2025",
        "data_validade": "14/11/2025",
        "cpf_cnpj_cliente": "93741880663",
        "nome_cliente": "GILSON GOMES DO CARMO",
        "quantidade_caixas": "140",
        "modelo_caixas": "6424"
    },
    {
        "numero_laudo": "0170093",
        "data_emissao": "30/10/2025",
        "data_validade": "14/11/2025",
        "cpf_cnpj_cliente": "93741880663",
        "nome_cliente": "GILSON GOMES DO CARMO",
        "quantidade_caixas": "140",
        "modelo_caixas": "6424"
    },
    {
        "numero_laudo": "0170094",
        "data_emissao": "30/10/2025",
        "data_validade": "14/11/2025",
        "cpf_cnpj_cliente": "93741880663",
        "nome_cliente": "GILSON GOMES DO CARMO",
        "quantidade_caixas": "140",
        "modelo_caixas": "6424"
    },
    {
        "numero_laudo": "0170095",
        "data_emissao": "30/10/2025",
        "data_validade": "14/11/2025",
        "cpf_cnpj_cliente": "93741880663",
        "nome_cliente": "GILSON GOMES DO CARMO",
        "quantidade_caixas": "140",
        "modelo_caixas": "6424"
    },
    {
        "numero_laudo": "0170096",
        "data_emissao": "30/10/2025",
        "data_validade": "14/11/2025",
        "cpf_cnpj_cliente": "93741880663",
        "nome_cliente": "GILSON GOMES DO CARMO",
        "quantidade_caixas": "140",
        "modelo_caixas": "6424"
    },
    {
        "numero_laudo": "0170097",
        "data_emissao": "30/10/2025",
        "data_validade": "14/11/2025",
        "cpf_cnpj_cliente": "93741880663",
        "nome_cliente": "GILSON GOMES DO CARMO",
        "quantidade_caixas": "140",
        "modelo_caixas": "6424"
    },
    {
        "numero_laudo": "0170098",
        "data_emissao": "30/10/2025",
        "data_validade": "14/11/2025",
        "cpf_cnpj_cliente": "93741880663",
        "nome_cliente": "GILSON GOMES DO CARMO",
        "quantidade_caixas": "150",
        "modelo_caixas": "6424"
    },
    {
        "numero_laudo": "0170099",
        "data_emissao": "30/10/2025",
        "data_validade": "14/11/2025",
        "cpf_cnpj_cliente": "93741880663",
        "nome_cliente": "GILSON GOMES DO CARMO",
        "quantidade_caixas": "150",
        "modelo_caixas": "6424"
    },
    {
        "numero_laudo": "0170100",
        "data_emissao": "30/10/2025",
        "data_validade": "14/11/2025",
        "cpf_cnpj_cliente": "41.857.334/0001-63",
        "nome_cliente": "COMERCIAL NOVA ERA BH LTDA",
        "quantidade_caixas": "234",
        "modelo_caixas": "6424"
    },
    {
        "numero_laudo": "0170101",
        "data_emissao": "30/10/2025",
        "data_validade": "14/11/2025",
        "cpf_cnpj_cliente": "41.857.334/0001-63",
        "nome_cliente": "COMERCIAL NOVA ERA BH LTDA",
        "quantidade_caixas": "234",
        "modelo_caixas": "6424"
    },
    {
        "numero_laudo": "0170102",
        "data_emissao": "30/10/2025",
        "data_validade": "14/11/2025",
        "cpf_cnpj_cliente": "41.857.334/0001-63",
        "nome_cliente": "COMERCIAL NOVA ERA BH LTDA",
        "quantidade_caixas": "234",
        "modelo_caixas": "6424"
    },
    {
        "numero_laudo": "0170103",
        "data_emissao": "30/10/2025",
        "data_validade": "14/11/2025",
        "cpf_cnpj_cliente": "41.857.334/0001-63",
        "nome_cliente": "COMERCIAL NOVA ERA BH LTDA",
        "quantidade_caixas": "234",
        "modelo_caixas": "6424"
    },
    {
        "numero_laudo": "0170104",
        "data_emissao": "30/10/2025",
        "data_validade": "14/11/2025",
        "cpf_cnpj_cliente": "41.851.003/0001-16",
        "nome_cliente": "CVD ALIMENTOS LTDA",
        "quantidade_caixas": "191",
        "modelo_caixas": "6424"
    },
    {
        "numero_laudo": "0170105",
        "data_emissao": "30/10/2025",
        "data_validade": "14/11/2025",
        "cpf_cnpj_cliente": "41.851.003/0001-16",
        "nome_cliente": "CVD ALIMENTOS LTDA",
        "quantidade_caixas": "191",
        "modelo_caixas": "6424"
    },
    {
        "numero_laudo": "0170106",
        "data_emissao": "30/10/2025",
        "data_validade": "14/11/2025",
        "cpf_cnpj_cliente": "644.635.166-68",
        "nome_cliente": "RONALDO DE FREITAS CAMPOS",
        "quantidade_caixas": "100",
        "modelo_caixas": "6424"
    },
    {
        "numero_laudo": "0170107",
        "data_emissao": "30/10/2025",
        "data_validade": "14/11/2025",
        "cpf_cnpj_cliente": "644.635.166-68",
        "nome_cliente": "RONALDO DE FREITAS CAMPOS",
        "quantidade_caixas": "100",
        "modelo_caixas": "6424"
    },
    {
        "numero_laudo": "0170108",
        "data_emissao": "30/10/2025",
        "data_validade": "14/11/2025",
        "cpf_cnpj_cliente": "644.635.166-68",
        "nome_cliente": "RONALDO DE FREITAS CAMPOS",
        "quantidade_caixas": "100",
        "modelo_caixas": "6424"
    },
    {
        "numero_laudo": "0170109",
        "data_emissao": "30/10/2025",
        "data_validade": "14/11/2025",
        "cpf_cnpj_cliente": "138.873.336-67",
        "nome_cliente": "WELLINGNTON ALVES DE SOUSA",
        "quantidade_caixas": "200",
        "modelo_caixas": "6424"
    },
    {
        "numero_laudo": "0170110",
        "data_emissao": "30/10/2025",
        "data_validade": "14/11/2025",
        "cpf_cnpj_cliente": "138.873.336-67",
        "nome_cliente": "WELLINGNTON ALVES DE SOUSA",
        "quantidade_caixas": "200",
        "modelo_caixas": "6424"
    },
    {
        "numero_laudo": "0170111",
        "data_emissao": "30/10/2025",
        "data_validade": "14/11/2025",
        "cpf_cnpj_cliente": "138.873.336-67",
        "nome_cliente": "WELLINGNTON ALVES DE SOUSA",
        "quantidade_caixas": "200",
        "modelo_caixas": "6424"
    },
    {
        "numero_laudo": "0170112",
        "data_emissao": "30/10/2025",
        "data_validade": "14/11/2025",
        "cpf_cnpj_cliente": "138.873.336-67",
        "nome_cliente": "WELLINGNTON ALVES DE SOUSA",
        "quantidade_caixas": "200",
        "modelo_caixas": "6424"
    },
    {
        "numero_laudo": "0170113",
        "data_emissao": "31/10/2025",
        "data_validade": "15/11/2025",
        "cpf_cnpj_cliente": "41857334000163",
        "nome_cliente": "COMERCIAL NOVA ERA BH LTDA",
        "quantidade_caixas": "234",
        "modelo_caixas": "6424"
    },
    {
        "numero_laudo": "0170114",
        "data_emissao": "31/10/2025",
        "data_validade": "15/11/2025",
        "cpf_cnpj_cliente": "41857334000163",
        "nome_cliente": "COMERCIAL NOVA ERA BH LTDA",
        "quantidade_caixas": "234",
        "modelo_caixas": "6424"
    },
    {
        "numero_laudo": "0170115",
        "data_emissao": "31/10/2025",
        "data_validade": "15/11/2025",
        "cpf_cnpj_cliente": "41857334000163",
        "nome_cliente": "COMERCIAL NOVA ERA BH LTDA",
        "quantidade_caixas": "234",
        "modelo_caixas": "6424"
    },
    {
        "numero_laudo": "0170116",
        "data_emissao": "31/10/2025",
        "data_validade": "15/11/2025",
        "cpf_cnpj_cliente": "41857334000163",
        "nome_cliente": "COMERCIAL NOVA ERA BH LTDA",
        "quantidade_caixas": "234",
        "modelo_caixas": "6424"
    },
    {
        "numero_laudo": "0170117",
        "data_emissao": "31/10/2025",
        "data_validade": "15/11/2025",
        "cpf_cnpj_cliente": "19.886.150/0005-04",
        "nome_cliente": "UVALE FRUTAS TROPICAIS ",
        "quantidade_caixas": "400",
        "modelo_caixas": "6424"
    },
    {
        "numero_laudo": "0170118",
        "data_emissao": "31/10/2025",
        "data_validade": "15/11/2025",
        "cpf_cnpj_cliente": "19.886.150/0005-04",
        "nome_cliente": "UVALE FRUTAS TROPICAIS ",
        "quantidade_caixas": "400",
        "modelo_caixas": "6424"
    },
    {
        "numero_laudo": "0170119",
        "data_emissao": "01/11/2025",
        "data_validade": "16/11/2025",
        "cpf_cnpj_cliente": "19.886.150/0005-04",
        "nome_cliente": "UVALE FRUTAS TROPICAIS ",
        "quantidade_caixas": "800",
        "modelo_caixas": "6424"
    },
    {
        "numero_laudo": "0170121",
        "data_emissao": "03/11/2025",
        "data_validade": "18/11/2025",
        "cpf_cnpj_cliente": "41.851.003/0001-16",
        "nome_cliente": "CVD ALIMENTOS LTDA",
        "quantidade_caixas": "529",
        "modelo_caixas": "6424"
    },
    {
        "numero_laudo": "0170122",
        "data_emissao": "03/11/2025",
        "data_validade": "18/11/2025",
        "cpf_cnpj_cliente": "41.851.003/0001-16",
        "nome_cliente": "UVALE FRUTAS TROPICAIS ",
        "quantidade_caixas": "800",
        "modelo_caixas": "6424"
    },
    {
        "numero_laudo": "0170123",
        "data_emissao": "03/11/2025",
        "data_validade": "18/11/2025",
        "cpf_cnpj_cliente": "119.783.106-17",
        "nome_cliente": "FABRICIO JOSÉ FELIPE",
        "quantidade_caixas": "182",
        "modelo_caixas": "6424"
    },
    {
        "numero_laudo": "0170124",
        "data_emissao": "04/11/2025",
        "data_validade": "19/11/2025",
        "cpf_cnpj_cliente": "119.465.236-07",
        "nome_cliente": "JOÃO MARCOS",
        "quantidade_caixas": "390",
        "modelo_caixas": "6424"
    },
    {
        "numero_laudo": "0170125",
        "data_emissao": "04/11/2025",
        "data_validade": "19/11/2025",
        "cpf_cnpj_cliente": "119.465.236-07",
        "nome_cliente": "JOÃO MARCOS",
        "quantidade_caixas": "390",
        "modelo_caixas": "6424"
    },
    {
        "numero_laudo": "0170126",
        "data_emissao": "04/11/2025",
        "data_validade": "19/11/2025",
        "cpf_cnpj_cliente": "108.313.156-79",
        "nome_cliente": "MARCOS GOMES DE OLIVEIRA",
        "quantidade_caixas": "459",
        "modelo_caixas": "6424"
    },
    {
        "numero_laudo": "0170127",
        "data_emissao": "04/11/2025",
        "data_validade": "19/11/2025",
        "cpf_cnpj_cliente": "108.313.156-79",
        "nome_cliente": "MARCOS GOMES DE OLIVEIRA",
        "quantidade_caixas": "459",
        "modelo_caixas": "6424"
    },
    {
        "numero_laudo": "0170128",
        "data_emissao": "04/11/2025",
        "data_validade": "19/11/2025",
        "cpf_cnpj_cliente": "138.873.336-67",
        "nome_cliente": "WELLINGNTON ALVES DE SOUSA",
        "quantidade_caixas": "200",
        "modelo_caixas": "6424"
    },
    {
        "numero_laudo": "0170129",
        "data_emissao": "04/11/2025",
        "data_validade": "19/11/2025",
        "cpf_cnpj_cliente": "138.873.336-67",
        "nome_cliente": "WELLINGNTON ALVES DE SOUSA",
        "quantidade_caixas": "200",
        "modelo_caixas": "6424"
    },
    {
        "numero_laudo": "0170130",
        "data_emissao": "04/11/2025",
        "data_validade": "19/11/2025",
        "cpf_cnpj_cliente": "138.873.336-67",
        "nome_cliente": "WELLINGNTON ALVES DE SOUSA",
        "quantidade_caixas": "200",
        "modelo_caixas": "6424"
    },
    {
        "numero_laudo": "0170131",
        "data_emissao": "04/11/2025",
        "data_validade": "19/11/2025",
        "cpf_cnpj_cliente": "138.873.336-67",
        "nome_cliente": "WELLINGNTON ALVES DE SOUSA",
        "quantidade_caixas": "200",
        "modelo_caixas": "6424"
    },
    {
        "numero_laudo": "0170132",
        "data_emissao": "05/11/2025",
        "data_validade": "20/11/2025",
        "cpf_cnpj_cliente": "071.107.626-02",
        "nome_cliente": "CARLOS ALBERTO DA SILVA BENTO",
        "quantidade_caixas": "234",
        "modelo_caixas": "6424"
    },
    {
        "numero_laudo": "0170133",
        "data_emissao": "05/11/2025",
        "data_validade": "20/11/2025",
        "cpf_cnpj_cliente": "071.107.626-02",
        "nome_cliente": "CARLOS ALBERTO DA SILVA BENTO",
        "quantidade_caixas": "234",
        "modelo_caixas": "6424"
    },
    {
        "numero_laudo": "0170134",
        "data_emissao": "05/11/2025",
        "data_validade": "20/11/2025",
        "cpf_cnpj_cliente": "071.107.626-02",
        "nome_cliente": "CARLOS ALBERTO DA SILVA BENTO",
        "quantidade_caixas": "234",
        "modelo_caixas": "6424"
    },
    {
        "numero_laudo": "0170135",
        "data_emissao": "05/11/2025",
        "data_validade": "20/11/2025",
        "cpf_cnpj_cliente": "071.107.626-02",
        "nome_cliente": "CARLOS ALBERTO DA SILVA BENTO",
        "quantidade_caixas": "234",
        "modelo_caixas": "6424"
    },
    {
        "numero_laudo": "0170136",
        "data_emissao": "05/11/2025",
        "data_validade": "20/11/2025",
        "cpf_cnpj_cliente": "41.851.003/0001-16",
        "nome_cliente": "CVD ALIMENTOS LTDA",
        "quantidade_caixas": "516",
        "modelo_caixas": "6424"
    },
    {
        "numero_laudo": "0170137",
        "data_emissao": "05/11/2025",
        "data_validade": "20/11/2025",
        "cpf_cnpj_cliente": "41.851.003/0001-16",
        "nome_cliente": "CVD ALIMENTOS LTDA",
        "quantidade_caixas": "516",
        "modelo_caixas": "6424"
    },
    {
        "numero_laudo": "0170138",
        "data_emissao": "05/11/2025",
        "data_validade": "20/11/2025",
        "cpf_cnpj_cliente": "19.886.150/0005-04",
        "nome_cliente": "UVALE FRUTAS TROPICAIS ",
        "quantidade_caixas": "300",
        "modelo_caixas": "6424"
    },
    {
        "numero_laudo": "0170139",
        "data_emissao": "06/11/2025",
        "data_validade": "21/11/2025",
        "cpf_cnpj_cliente": "41.857.334/0001-63",
        "nome_cliente": "COMERCIAL NOVA ERA BH LTDA",
        "quantidade_caixas": "234",
        "modelo_caixas": "6424"
    },
    {
        "numero_laudo": "0170140",
        "data_emissao": "06/11/2025",
        "data_validade": "21/11/2025",
        "cpf_cnpj_cliente": "41.857.334/0001-63",
        "nome_cliente": "COMERCIAL NOVA ERA BH LTDA",
        "quantidade_caixas": "234",
        "modelo_caixas": "6424"
    },
    {
        "numero_laudo": "0170141",
        "data_emissao": "06/11/2025",
        "data_validade": "21/11/2025",
        "cpf_cnpj_cliente": "41.857.334/0001-63",
        "nome_cliente": "COMERCIAL NOVA ERA BH LTDA",
        "quantidade_caixas": "234",
        "modelo_caixas": "6424"
    },
    {
        "numero_laudo": "0170142",
        "data_emissao": "06/11/2025",
        "data_validade": "21/11/2025",
        "cpf_cnpj_cliente": "41.857.334/0001-63",
        "nome_cliente": "COMERCIAL NOVA ERA BH LTDA",
        "quantidade_caixas": "234",
        "modelo_caixas": "6424"
    },
    {
        "numero_laudo": "0170143",
        "data_emissao": "06/11/2025",
        "data_validade": "21/11/2025",
        "cpf_cnpj_cliente": "19.886.150/0005-04",
        "nome_cliente": "UVALE FRUTAS TROPICAIS ",
        "quantidade_caixas": "800",
        "modelo_caixas": "6424"
    },
    {
        "numero_laudo": "0170144",
        "data_emissao": "06/11/2025",
        "data_validade": "21/11/2025",
        "cpf_cnpj_cliente": "41.851.003/0001-16",
        "nome_cliente": "CVD ALIMENTOS LTDA",
        "quantidade_caixas": "325",
        "modelo_caixas": "6424"
    },
    {
        "numero_laudo": "0170145",
        "data_emissao": "06/11/2025",
        "data_validade": "21/11/2025",
        "cpf_cnpj_cliente": "41.851.003/0001-16",
        "nome_cliente": "CVD ALIMENTOS LTDA",
        "quantidade_caixas": "325",
        "modelo_caixas": "6424"
    },
    {
        "numero_laudo": "0170146",
        "data_emissao": "07/11/2025",
        "data_validade": "22/11/2025",
        "cpf_cnpj_cliente": "937.418.806-63",
        "nome_cliente": "GILSON GOMES DO CARMO",
        "quantidade_caixas": "6424",
        "modelo_caixas": "154"
    },
    {
        "numero_laudo": "0170147",
        "data_emissao": "07/11/2025",
        "data_validade": "22/11/2025",
        "cpf_cnpj_cliente": "937.418.806-63",
        "nome_cliente": "GILSON GOMES DO CARMO",
        "quantidade_caixas": "6424",
        "modelo_caixas": "154"
    },
    {
        "numero_laudo": "0170148",
        "data_emissao": "07/11/2025",
        "data_validade": "22/11/2025",
        "cpf_cnpj_cliente": "937.418.806-63",
        "nome_cliente": "GILSON GOMES DO CARMO",
        "quantidade_caixas": "6424",
        "modelo_caixas": "154"
    },
    {
        "numero_laudo": "0170149",
        "data_emissao": "07/11/2025",
        "data_validade": "22/11/2025",
        "cpf_cnpj_cliente": "937.418.806-63",
        "nome_cliente": "GILSON GOMES DO CARMO",
        "quantidade_caixas": "6424",
        "modelo_caixas": "154"
    },
    {
        "numero_laudo": "0170150",
        "data_emissao": "07/11/2025",
        "data_validade": "22/11/2025",
        "cpf_cnpj_cliente": "937.418.806-63",
        "nome_cliente": "GILSON GOMES DO CARMO",
        "quantidade_caixas": "6424",
        "modelo_caixas": "154"
    },
    {
        "numero_laudo": "0170151",
        "data_emissao": "07/11/2025",
        "data_validade": "22/11/2025",
        "cpf_cnpj_cliente": "937.418.806-63",
        "nome_cliente": "GILSON GOMES DO CARMO",
        "quantidade_caixas": "6424",
        "modelo_caixas": "154"
    },
    {
        "numero_laudo": "0170152",
        "data_emissao": "07/11/2025",
        "data_validade": "22/11/2025",
        "cpf_cnpj_cliente": "937.418.806-63",
        "nome_cliente": "GILSON GOMES DO CARMO",
        "quantidade_caixas": "6424",
        "modelo_caixas": "154"
    },
    {
        "numero_laudo": "0170153",
        "data_emissao": "07/11/2025",
        "data_validade": "22/11/2025",
        "cpf_cnpj_cliente": "937.418.806-63",
        "nome_cliente": "GILSON GOMES DO CARMO",
        "quantidade_caixas": "6424",
        "modelo_caixas": "154"
    },
    {
        "numero_laudo": "0170154",
        "data_emissao": "07/11/2025",
        "data_validade": "22/11/2025",
        "cpf_cnpj_cliente": "937.418.806-63",
        "nome_cliente": "GILSON GOMES DO CARMO",
        "quantidade_caixas": "6424",
        "modelo_caixas": "154"
    },
    {
        "numero_laudo": "0170155",
        "data_emissao": "07/11/2025",
        "data_validade": "22/11/2025",
        "cpf_cnpj_cliente": "937.418.806-63",
        "nome_cliente": "GILSON GOMES DO CARMO",
        "quantidade_caixas": "6424",
        "modelo_caixas": "154"
    },
    {
        "numero_laudo": "0170156",
        "data_emissao": "07/11/2025",
        "data_validade": "22/11/2025",
        "cpf_cnpj_cliente": "41.851.003/0001-16",
        "nome_cliente": "CVD ALIMENTOS LTDA",
        "quantidade_caixas": "560",
        "modelo_caixas": "6424"
    },
    {
        "numero_laudo": "0170157",
        "data_emissao": "10/11/2025",
        "data_validade": "25/11/2025",
        "cpf_cnpj_cliente": "41.851.003/0001-16",
        "nome_cliente": "CVD ALIMENTOS LTDA",
        "quantidade_caixas": "435",
        "modelo_caixas": "6424"
    },
    {
        "numero_laudo": "0170158",
        "data_emissao": "11/11/2025",
        "data_validade": "26/11/2025",
        "cpf_cnpj_cliente": "41857334000163",
        "nome_cliente": "COMERCIAL NOVA ERA BH LTDA",
        "quantidade_caixas": "",
        "modelo_caixas": ""
    },
    {
        "numero_laudo": "0170159",
        "data_emissao": "11/11/2025",
        "data_validade": "26/11/2025",
        "cpf_cnpj_cliente": "41857334000163",
        "nome_cliente": "COMERCIAL NOVA ERA BH LTDA",
        "quantidade_caixas": "234",
        "modelo_caixas": "6424"
    },
    {
        "numero_laudo": "0170160",
        "data_emissao": "11/11/2025",
        "data_validade": "26/11/2025",
        "cpf_cnpj_cliente": "41857334000163",
        "nome_cliente": "COMERCIAL NOVA ERA BH LTDA",
        "quantidade_caixas": "234",
        "modelo_caixas": "6424"
    },
    {
        "numero_laudo": "0170161",
        "data_emissao": "11/11/2025",
        "data_validade": "26/11/2025",
        "cpf_cnpj_cliente": "41.857.334/0001-63",
        "nome_cliente": "COMERCIAL NOVA ERA BH LTDA",
        "quantidade_caixas": "234",
        "modelo_caixas": "6424"
    },
    {
        "numero_laudo": "0170162",
        "data_emissao": "11/11/2025",
        "data_validade": "26/11/2025",
        "cpf_cnpj_cliente": "41.857.334/0001-63",
        "nome_cliente": "COMERCIAL NOVA ERA BH LTDA",
        "quantidade_caixas": "234",
        "modelo_caixas": "234"
    },
    {
        "numero_laudo": "0170163",
        "data_emissao": "11/11/2025",
        "data_validade": "26/11/2025",
        "cpf_cnpj_cliente": " 11946523607",
        "nome_cliente": " JOÃO MARCOS",
        "quantidade_caixas": "780",
        "modelo_caixas": "6424"
    },
    {
        "numero_laudo": "0170164",
        "data_emissao": "11/11/2025",
        "data_validade": "26/11/2025",
        "cpf_cnpj_cliente": " 11946523607",
        "nome_cliente": " JOÃO MARCOS",
        "quantidade_caixas": "780",
        "modelo_caixas": "6424"
    },
    {
        "numero_laudo": "0170165",
        "data_emissao": "11/11/2025",
        "data_validade": "26/11/2025",
        "cpf_cnpj_cliente": "19.886.150/0005-04",
        "nome_cliente": "UVALE FRUTAS TROPICAIS ",
        "quantidade_caixas": "800",
        "modelo_caixas": "6424"
    },
    {
        "numero_laudo": "0170166",
        "data_emissao": "12/11/2025",
        "data_validade": "27/11/2025",
        "cpf_cnpj_cliente": "41.857.334/0001-63",
        "nome_cliente": "COMERCIAL NOVA ERA LTDA",
        "quantidade_caixas": "234",
        "modelo_caixas": "6424"
    },
    {
        "numero_laudo": "0170167",
        "data_emissao": "12/11/2025",
        "data_validade": "27/11/2025",
        "cpf_cnpj_cliente": "41.857.334/0001-63",
        "nome_cliente": "COMERCIAL NOVA ERA LTDA",
        "quantidade_caixas": "234",
        "modelo_caixas": "6424"
    },
    {
        "numero_laudo": "0170168",
        "data_emissao": "12/11/2025",
        "data_validade": "27/11/2025",
        "cpf_cnpj_cliente": "41.857.334/0001-63",
        "nome_cliente": "COMERCIAL NOVA ERA LTDA",
        "quantidade_caixas": "234",
        "modelo_caixas": "6424"
    },
    {
        "numero_laudo": "0170169",
        "data_emissao": "12/11/2025",
        "data_validade": "27/11/2025",
        "cpf_cnpj_cliente": "41.857.334/0001-63",
        "nome_cliente": "COMERCIAL NOVA ERA LTDA",
        "quantidade_caixas": "234",
        "modelo_caixas": "6424"
    },
    {
        "numero_laudo": "0170172",
        "data_emissao": "24/11/2025",
        "data_validade": "09/12/2025",
        "cpf_cnpj_cliente": "108.313.156-79",
        "nome_cliente": "Marcos Gomes De Oliveira ",
        "quantidade_caixas": "540",
        "modelo_caixas": "6424"
    }
]